[
  {
    "id": 7,
    "topic": "Basic SQL Commands",
    "difficulty": "easy",
    "question": [
      {
        "type": "text",
        "value": "Which SQL statement is used to extract data from a database?"
      }
    ],
    "options": [
      {
        "label": "A",
        "type": "text",
        "value": "SELECT"
      },
      {
        "label": "B",
        "type": "text",
        "value": "EXTRACT"
      },
      {
        "label": "C",
        "type": "text",
        "value": "GET"
      },
      {
        "label": "D",
        "type": "text",
        "value": "PULL"
      }
    ],
    "correct": "A",
    "explanation": [
      {
        "type": "text",
        "value": "The SELECT statement is used to query the database and retrieve selected data that match the criteria that you specify."
      }
    ]
  },
  {
    "id": 2,
    "topic": "Functions and Aggregation",
    "difficulty": "easy",
    "question": [
      {
        "type": "text",
        "value": "Which SQL function is used to return the number of input rows that match a specific condition?"
      }
    ],
    "options": [
      {
        "label": "A",
        "type": "text",
        "value": "SUM()"
      },
      {
        "label": "B",
        "type": "text",
        "value": "COUNT()"
      },
      {
        "label": "C",
        "type": "text",
        "value": "MAX()"
      },
      {
        "label": "D",
        "type": "text",
        "value": "AVG()"
      }
    ],
    "correct": "B",
    "explanation": [
      {
        "type": "text",
        "value": "The COUNT() function is used to return the number of rows that match a specified condition."
      }
    ]
  },
  {
    "id": 5,
    "topic": "Joins",
    "difficulty": "easy",
    "question": [
      {
        "type": "text",
        "value": "Which SQL keyword is used to retrieve data from multiple tables based on a related column between them?"
      }
    ],
    "options": [
      {
        "label": "A",
        "type": "text",
        "value": "JOIN"
      },
      {
        "label": "B",
        "type": "text",
        "value": "CONNECT"
      },
      {
        "label": "C",
        "type": "text",
        "value": "RELATE"
      },
      {
        "label": "D",
        "type": "text",
        "value": "LINK"
      }
    ],
    "correct": "A",
    "explanation": [
      {
        "type": "text",
        "value": "The JOIN keyword is used in SQL to query data from two or more tables based on a relationship between certain columns in these tables."
      }
    ]
  },
  {
    "id": 4,
    "topic": "Filtering Data",
    "difficulty": "easy",
    "question": [
      {
        "type": "text",
        "value": "What is the correct SQL keyword to filter records based on a specified condition in a WHERE clause?"
      }
    ],
    "options": [
      {
        "label": "A",
        "type": "text",
        "value": "FILTER"
      },
      {
        "label": "B",
        "type": "text",
        "value": "WHERE"
      },
      {
        "label": "C",
        "type": "text",
        "value": "SELECT"
      },
      {
        "label": "D",
        "type": "text",
        "value": "CONDITION"
      }
    ],
    "correct": "B",
    "explanation": [
      {
        "type": "text",
        "value": "The correct keyword to use when filtering records based on a condition is 'WHERE'."
      }
    ]
  },
  {
    "id": 7,
    "topic": "Subqueries",
    "difficulty": "easy",
    "question": [
      {
        "type": "text",
        "value": "What is the result of a subquery that returns more than one row when used in a single row comparison operation?"
      }
    ],
    "options": [
      {
        "label": "A",
        "type": "text",
        "value": "Syntax error"
      },
      {
        "label": "B",
        "type": "text",
        "value": "Execution continues with a warning"
      },
      {
        "label": "C",
        "type": "text",
        "value": "Returns the first row only"
      },
      {
        "label": "D",
        "type": "text",
        "value": "Converts multiple rows into a single text"
      }
    ],
    "correct": "A",
    "explanation": [
      {
        "type": "text",
        "value": "A subquery returning more than one row when used in a context expecting a single row results in a syntax error as the operation cannot handle multiple rows."
      }
    ]
  },
  {
    "id": 6,
    "topic": "Data Types",
    "difficulty": "easy",
    "question": [
      {
        "type": "text",
        "value": "Which data type in MySQL is used to store boolean values?"
      }
    ],
    "options": [
      {
        "label": "A",
        "type": "text",
        "value": "BOOLEAN or TINYINT(1)"
      },
      {
        "label": "B",
        "type": "text",
        "value": "VARCHAR"
      },
      {
        "label": "C",
        "type": "text",
        "value": "INTEGER"
      },
      {
        "label": "D",
        "type": "text",
        "value": "FLOAT"
      }
    ],
    "correct": "A",
    "explanation": [
      {
        "type": "text",
        "value": "In MySQL, BOOLEAN is a synonym for TINYINT(1), used to represent boolean values as 0 (false) or 1 (true)."
      }
    ]
  },
  {
    "id": 8,
    "topic": "Joins",
    "difficulty": "easy",
    "question": [
      {
        "type": "text",
        "value": "Which SQL keyword is used to retrieve records from two or more tables based on a related column between them?"
      }
    ],
    "options": [
      {
        "label": "A",
        "type": "text",
        "value": "SELECT"
      },
      {
        "label": "B",
        "type": "text",
        "value": "JOIN"
      },
      {
        "label": "C",
        "type": "text",
        "value": "GROUP BY"
      },
      {
        "label": "D",
        "type": "text",
        "value": "WHERE"
      }
    ],
    "correct": "B",
    "explanation": [
      {
        "type": "text",
        "value": "The JOIN keyword is used in SQL to query data from two or more tables based on a relationship between certain columns in these tables."
      }
    ]
  },
  {
    "id": 8,
    "topic": "Data Retrieval with PHP and MySQL",
    "difficulty": "easy",
    "question": [
      {
        "type": "text",
        "value": "Which function is used to execute a SQL query in PHP?"
      }
    ],
    "options": [
      {
        "label": "A",
        "type": "text",
        "value": "$mysqli->query();"
      },
      {
        "label": "B",
        "type": "text",
        "value": "mysql_query();"
      },
      {
        "label": "C",
        "type": "text",
        "value": "execute_sql();"
      },
      {
        "label": "D",
        "type": "text",
        "value": "run_query();"
      }
    ],
    "correct": "A",
    "explanation": [
      {
        "type": "text",
        "value": "The $mysqli->query() function is used to execute a SQL query in PHP when using the MySQLi extension."
      }
    ]
  },
  {
    "id": 5,
    "topic": "Select Query Basics",
    "difficulty": "easy",
    "question": [
      {
        "type": "text",
        "value": "What does the SQL SELECT statement do in a query?"
      }
    ],
    "options": [
      {
        "label": "A",
        "type": "text",
        "value": "Retrieves specific data from one or more tables"
      },
      {
        "label": "B",
        "type": "text",
        "value": "Updates data in the database"
      },
      {
        "label": "C",
        "type": "text",
        "value": "Deletes data from the database"
      },
      {
        "label": "D",
        "type": "text",
        "value": "Creates a new table"
      }
    ],
    "correct": "A",
    "explanation": [
      {
        "type": "text",
        "value": "The SELECT statement is used to select data from a database. It retrieves data from one or more tables."
      }
    ]
  },
  {
    "id": 8,
    "topic": "User Privileges",
    "difficulty": "easy",
    "question": [
      {
        "type": "text",
        "value": "Which SQL statement is used to provide a user with specific privileges in MySQL?"
      }
    ],
    "options": [
      {
        "label": "A",
        "type": "text",
        "value": "GRANT"
      },
      {
        "label": "B",
        "type": "text",
        "value": "ALLOW"
      },
      {
        "label": "C",
        "type": "text",
        "value": "GIVE"
      },
      {
        "label": "D",
        "type": "text",
        "value": "ENABLE"
      }
    ],
    "correct": "A",
    "explanation": [
      {
        "type": "text",
        "value": "The 'GRANT' statement is used in MySQL to provide specific privileges to a user."
      }
    ]
  },
  {
    "id": 8,
    "topic": "Sorting Results",
    "difficulty": "medium",
    "question": [
      {
        "type": "text",
        "value": "What is the result of the SQL query SELECT Name FROM Employees ORDER BY Hiring_Date DESC LIMIT 3;"
      }
    ],
    "options": [
      {
        "label": "A",
        "type": "text",
        "value": "The names of the first 3 employees when ordered by their hiring date from the earliest to the latest"
      },
      {
        "label": "B",
        "type": "text",
        "value": "The names of all employees ordered by their hiring date from the latest to the earliest"
      },
      {
        "label": "C",
        "type": "text",
        "value": "The names of the last 3 employees hired"
      },
      {
        "label": "D",
        "type": "text",
        "value": "The names of the first 3 employees when ordered by their hiring date from the latest to the earliest"
      }
    ],
    "correct": "D",
    "explanation": [
      {
        "type": "text",
        "value": "Option D is correct because the query specifies 'ORDER BY Hiring_Date DESC' which sorts the employees by hiring date from latest to earliest, and 'LIMIT 3' picks the top 3 from this sorted list."
      }
    ]
  },
  {
    "id": 7,
    "topic": "Index Optimization",
    "difficulty": "medium",
    "question": [
      {
        "type": "text",
        "value": "What type of index would most efficiently optimize a query that searches based on the first few characters of a string column in MySQL?"
      }
    ],
    "options": [
      {
        "label": "A",
        "type": "text",
        "value": "Hash Index"
      },
      {
        "label": "B",
        "type": "text",
        "value": "B-Tree Index"
      },
      {
        "label": "C",
        "type": "text",
        "value": "Full-Text Index"
      },
      {
        "label": "D",
        "type": "text",
        "value": "Spatial Index"
      }
    ],
    "correct": "B",
    "explanation": [
      {
        "type": "text",
        "value": "B-Tree indexes are most suitable for high-performance for queries that involve searching the start of strings because they maintain data in a sorted order and support partial-text matches efficiently."
      }
    ]
  },
  {
    "id": 6,
    "topic": "Query Optimization",
    "difficulty": "medium",
    "question": [
      {
        "type": "text",
        "value": "What is the best practice when using JOIN in SQL queries to optimize performance?"
      }
    ],
    "options": [
      {
        "label": "A",
        "type": "text",
        "value": "Using RIGHT JOIN instead of LEFT JOIN"
      },
      {
        "label": "B",
        "type": "text",
        "value": "Joining tables based on columns without indexes"
      },
      {
        "label": "C",
        "type": "text",
        "value": "Avoiding unnecessary columns in the SELECT statement"
      },
      {
        "label": "D",
        "type": "text",
        "value": "Always using NATURAL JOIN"
      }
    ],
    "correct": "C",
    "explanation": [
      {
        "type": "text",
        "value": "To optimize JOIN operations, one should avoid selecting unnecessary columns to minimize the amount of data processed and transferred in the query."
      }
    ]
  },
  {
    "id": 1,
    "topic": "Transaction Control",
    "difficulty": "medium",
    "question": [
      {
        "type": "text",
        "value": "Which statement is used to manually commit a transaction in MySQL?"
      }
    ],
    "options": [
      {
        "label": "A",
        "type": "text",
        "value": "COMMIT;"
      },
      {
        "label": "B",
        "type": "text",
        "value": "SAVEPOINT;"
      },
      {
        "label": "C",
        "type": "text",
        "value": "ROLLBACK;"
      },
      {
        "label": "D",
        "type": "text",
        "value": "START TRANSACTION;"
      }
    ],
    "correct": "A",
    "explanation": [
      {
        "type": "text",
        "value": "The COMMIT statement is used to save all changes made in the current transaction to the database."
      }
    ]
  },
  {
    "id": 4,
    "topic": "Indexing",
    "difficulty": "medium",
    "question": [
      {
        "type": "text",
        "value": "What is the main advantage of adding an index to a database column?"
      }
    ],
    "options": [
      {
        "label": "A",
        "type": "text",
        "value": "Decreases storage space"
      },
      {
        "label": "B",
        "type": "text",
        "value": "Increases query processing time"
      },
      {
        "label": "C",
        "type": "text",
        "value": "Improves the speed of data retrieval"
      },
      {
        "label": "D",
        "type": "text",
        "value": "Allows more data to be stored"
      }
    ],
    "correct": "C",
    "explanation": [
      {
        "type": "text",
        "value": "Adding an index on a database column primarily enhances the speed of data retrieval operations by allowing faster traversal of the indexed field, especially in large datasets."
      }
    ]
  },
  {
    "id": 10,
    "topic": "Data Manipulation with MySQL and PHP",
    "difficulty": "medium",
    "question": [
      {
        "type": "text",
        "value": "What is the correct way to execute a MySQL query in PHP?"
      }
    ],
    "options": [
      {
        "label": "A",
        "type": "text",
        "value": "$mysqli->query('SELECT * FROM users');"
      },
      {
        "label": "B",
        "type": "text",
        "value": "$mysqli.execute('SELECT * FROM users');"
      },
      {
        "label": "C",
        "type": "text",
        "value": "mysqli_query($mysqli, 'SELECT * FROM users');"
      },
      {
        "label": "D",
        "type": "text",
        "value": "execute_mysql_query('SELECT * FROM users');"
      }
    ],
    "correct": "A",
    "explanation": [
      {
        "type": "text",
        "value": "The correct way to execute a query in an object-oriented style is using the query method on a mysqli object, as shown in option A."
      }
    ]
  },
  {
    "id": 7,
    "topic": "Using Joins",
    "difficulty": "medium",
    "question": [
      {
        "type": "text",
        "value": "What will be the result of the following SQL query? SELECT a.name FROM employees a INNER JOIN departments b ON a.dept_id = b.id WHERE b.name = 'HR';"
      }
    ],
    "options": [
      {
        "label": "A",
        "type": "text",
        "value": "Returns names of all employees who work in the HR department."
      },
      {
        "label": "B",
        "type": "text",
        "value": "Returns names of all departments."
      },
      {
        "label": "C",
        "type": "text",
        "value": "Returns the total number of employees in the HR department."
      },
      {
        "label": "D",
        "type": "text",
        "value": "Returns an error because the query syntax is incorrect."
      }
    ],
    "correct": "A",
    "explanation": [
      {
        "type": "text",
        "value": "The SQL query correctly uses an INNER JOIN to combine rows from 'employees' and 'departments' where the department ID matches and the department's name is 'HR'. It then selects the names of the employees in this department."
      }
    ]
  },
  {
    "id": 10,
    "topic": "Query Optimization Techniques",
    "difficulty": "medium",
    "question": [
      {
        "type": "text",
        "value": "What is the primary benefit of using query caching in MySQL?"
      }
    ],
    "options": [
      {
        "label": "A",
        "type": "text",
        "value": "Increases data redundancy"
      },
      {
        "label": "B",
        "type": "text",
        "value": "Decreases storage space requirements"
      },
      {
        "label": "C",
        "type": "text",
        "value": "Reduces the load on the database"
      },
      {
        "label": "D",
        "type": "text",
        "value": "Automatically updates indices"
      }
    ],
    "correct": "C",
    "explanation": [
      {
        "type": "text",
        "value": "Query caching in MySQL stores the result set of a query in the cache and reuses the result for the same query, which reduces the load on the database by avoiding the need to execute the query again."
      }
    ]
  },
  {
    "id": 4,
    "topic": "Data Retrieval Techniques",
    "difficulty": "medium",
    "question": [
      {
        "type": "text",
        "value": "Which MySQL function is best suited for fetching multiple rows of data in a PHP application?"
      }
    ],
    "options": [
      {
        "label": "A",
        "type": "text",
        "value": "mysql_fetch_row()"
      },
      {
        "label": "B",
        "type": "text",
        "value": "mysql_fetch_array()"
      },
      {
        "label": "C",
        "type": "text",
        "value": "mysql_query()"
      },
      {
        "label": "D",
        "type": "text",
        "value": "mysql_fetch_assoc()"
      }
    ],
    "correct": "D",
    "explanation": [
      {
        "type": "text",
        "value": "The function mysql_fetch_assoc() is particularly useful for fetching multiple rows of data as it returns an associative array that corresponds to the fetched row and moves the internal data pointer ahead."
      }
    ]
  },
  {
    "id": 9,
    "topic": "Connecting MySQL with PHP",
    "difficulty": "medium",
    "question": [
      {
        "type": "text",
        "value": "Which PHP function is used to establish a connection with a MySQL database?"
      }
    ],
    "options": [
      {
        "label": "A",
        "type": "text",
        "value": "mysqli_connect()"
      },
      {
        "label": "B",
        "type": "text",
        "value": "mysql_connect()"
      },
      {
        "label": "C",
        "type": "text",
        "value": "connect_db()"
      },
      {
        "label": "D",
        "type": "text",
        "value": "db_connect()"
      }
    ],
    "correct": "A",
    "explanation": [
      {
        "type": "text",
        "value": "mysqli_connect() is the correct function to use for establishing a connection to a MySQL database using PHP, especially since mysql_connect() is deprecated."
      }
    ]
  },
  {
    "id": 10,
    "topic": "Data Types",
    "difficulty": "medium",
    "question": [
      {
        "type": "text",
        "value": "Which data type would be best for storing an IP address in MySQL?"
      }
    ],
    "options": [
      {
        "label": "A",
        "type": "text",
        "value": "VARCHAR(15)"
      },
      {
        "label": "B",
        "type": "text",
        "value": "CHAR(15)"
      },
      {
        "label": "C",
        "type": "text",
        "value": "BINARY(4)"
      },
      {
        "label": "D",
        "type": "text",
        "value": "VARBINARY(16)"
      }
    ],
    "correct": "A",
    "explanation": [
      {
        "type": "text",
        "value": "VARCHAR(15) is typically used for storing IP addresses to accommodate the variable length and the dot notation."
      }
    ]
  },
  {
    "id": 5,
    "topic": "Data Insertion in MySQL",
    "difficulty": "medium",
    "question": [
      {
        "type": "text",
        "value": "Which SQL statement is used to insert new data in a database?"
      }
    ],
    "options": [
      {
        "label": "A",
        "type": "text",
        "value": "INSERT INTO"
      },
      {
        "label": "B",
        "type": "text",
        "value": "ADD RECORD"
      },
      {
        "label": "C",
        "type": "text",
        "value": "CREATE DATA"
      },
      {
        "label": "D",
        "type": "text",
        "value": "NEW ENTRY"
      }
    ],
    "correct": "A",
    "explanation": [
      {
        "type": "text",
        "value": "The 'INSERT INTO' statement is used in SQL to insert new records into a table."
      }
    ]
  },
  {
    "id": 6,
    "topic": "Transaction Control",
    "difficulty": "medium",
    "question": [
      {
        "type": "text",
        "value": "Which statement can be used to undo transactions that have not yet been saved to the database?"
      }
    ],
    "options": [
      {
        "label": "A",
        "type": "text",
        "value": "COMMIT"
      },
      {
        "label": "B",
        "type": "text",
        "value": "SAVEPOINT"
      },
      {
        "label": "C",
        "type": "text",
        "value": "ROLLBACK"
      },
      {
        "label": "D",
        "type": "text",
        "value": "UNDO"
      }
    ],
    "correct": "C",
    "explanation": [
      {
        "type": "text",
        "value": "The 'ROLLBACK' statement is used to undo transactions that have not yet been committed to the database."
      }
    ]
  },
  {
    "id": 3,
    "topic": "Connection Handling",
    "difficulty": "medium",
    "question": [
      {
        "type": "text",
        "value": "What is the primary benefit of using persistent connections in MySQL when integrating with dynamic websites?"
      }
    ],
    "options": [
      {
        "label": "A",
        "type": "text",
        "value": "Reduces connection overhead for the web application."
      },
      {
        "label": "B",
        "type": "text",
        "value": "Increases the security of the database."
      },
      {
        "label": "C",
        "type": "text",
        "value": "Allows direct manipulation of SQL queries."
      },
      {
        "label": "D",
        "type": "text",
        "value": "Decreases the performance of the website."
      }
    ],
    "correct": "A",
    "explanation": [
      {
        "type": "text",
        "value": "Persistent connections mainly help in reducing the overhead associated with establishing connections repeatedly, thus potentially speeding up the interaction between the web application and the database."
      }
    ]
  },
  {
    "id": 9,
    "topic": "Index Optimization",
    "difficulty": "medium",
    "question": [
      {
        "type": "text",
        "value": "Which type of index will most effectively optimize a query that selects a range of values from a MySQL table?"
      }
    ],
    "options": [
      {
        "label": "A",
        "type": "text",
        "value": "Hash Index"
      },
      {
        "label": "B",
        "type": "text",
        "value": "B-Tree Index"
      },
      {
        "label": "C",
        "type": "text",
        "value": "Full-text Index"
      },
      {
        "label": "D",
        "type": "text",
        "value": "Spatial Index"
      }
    ],
    "correct": "B",
    "explanation": [
      {
        "type": "text",
        "value": "B-Tree Indexes are most effective for range queries as they keep data sorted and allow searches, sequential access, insertions, and deletions in logarithmic time."
      }
    ]
  },
  {
    "id": 1,
    "topic": "Connecting to MySQL with PHP",
    "difficulty": "medium",
    "question": [
      {
        "type": "text",
        "value": "Which PHP function is used to open a new connection to the MySQL server?"
      }
    ],
    "options": [
      {
        "label": "A",
        "type": "text",
        "value": "mysql_connect()"
      },
      {
        "label": "B",
        "type": "text",
        "value": "mysqli_connect()"
      },
      {
        "label": "C",
        "type": "text",
        "value": "connect_mysql()"
      },
      {
        "label": "D",
        "type": "text",
        "value": "mysql_connection()"
      }
    ],
    "correct": "B",
    "explanation": [
      {
        "type": "text",
        "value": "mysqli_connect() is the correct function to establish a new connection to a MySQL database using PHP. mysql_connect() was used in older PHP versions and is now deprecated."
      }
    ]
  },
  {
    "id": 5,
    "topic": "Connecting MySQL with PHP",
    "difficulty": "medium",
    "question": [
      {
        "type": "text",
        "value": "Which function in PHP would you use to execute a query that does not return a result set?"
      }
    ],
    "options": [
      {
        "label": "A",
        "type": "text",
        "value": "mysql_query()"
      },
      {
        "label": "B",
        "type": "text",
        "value": "mysqli_query()"
      },
      {
        "label": "C",
        "type": "text",
        "value": "mysqli_exec()"
      },
      {
        "label": "D",
        "type": "text",
        "value": "mysqli_real_query()"
      }
    ],
    "correct": "D",
    "explanation": [
      {
        "type": "text",
        "value": "mysqli_real_query() is used for executing SQL queries that do not return a result set, such as INSERT, UPDATE, DELETE."
      }
    ]
  },
  {
    "id": 9,
    "topic": "SELECT Statements",
    "difficulty": "medium",
    "question": [
      {
        "type": "text",
        "value": "What does the SQL query 'SELECT * FROM Customers WHERE Age > 30 AND City = 'New York';' return?"
      }
    ],
    "options": [
      {
        "label": "A",
        "type": "text",
        "value": "All records from Customers where Age is greater than 30 and City is New York"
      },
      {
        "label": "B",
        "type": "text",
        "value": "All records from Customers where Age is less than 30 and City is New York"
      },
      {
        "label": "C",
        "type": "text",
        "value": "All records from Customers where Age is greater than 30 or City is New York"
      },
      {
        "label": "D",
        "type": "text",
        "value": "No records from Customers"
      }
    ],
    "correct": "A",
    "explanation": [
      {
        "type": "text",
        "value": "The SQL query specifies a condition with 'AND', meaning both conditions must be satisfied: Age must be over 30, and City must be New York."
      }
    ]
  },
  {
    "id": 10,
    "topic": "Subqueries",
    "difficulty": "medium",
    "question": [
      {
        "type": "text",
        "value": "In MySQL, which type of subquery can be used in the FROM clause of a SELECT statement?"
      }
    ],
    "options": [
      {
        "label": "A",
        "type": "text",
        "value": "Scalar subquery"
      },
      {
        "label": "B",
        "type": "text",
        "value": "Row subquery"
      },
      {
        "label": "C",
        "type": "text",
        "value": "Table subquery"
      },
      {
        "label": "D",
        "type": "text",
        "value": "Correlated subquery"
      }
    ],
    "correct": "C",
    "explanation": [
      {
        "type": "text",
        "value": "A table subquery, also known as a derived table, can be used in the FROM clause to provide a set of rows for the main SELECT statement to process."
      }
    ]
  },
  {
    "id": 4,
    "topic": "User Authentication",
    "difficulty": "medium",
    "question": [
      {
        "type": "text",
        "value": "What does the REQUIRE clause in MySQL user account management do?"
      }
    ],
    "options": [
      {
        "label": "A",
        "type": "text",
        "value": "It specifies table-level privileges."
      },
      {
        "label": "B",
        "type": "text",
        "value": "It mandates that users must change their password upon first login."
      },
      {
        "label": "C",
        "type": "text",
        "value": "It imposes conditions for encrypted connection requirements."
      },
      {
        "label": "D",
        "type": "text",
        "value": "It sets the default storage engine for the user."
      }
    ],
    "correct": "C",
    "explanation": [
      {
        "type": "text",
        "value": "The REQUIRE clause is used in MySQL to specify that a user must connect using a secure, encrypted connection, thus option C is correct."
      }
    ]
  },
  {
    "id": 2,
    "topic": "Subqueries",
    "difficulty": "medium",
    "question": [
      {
        "type": "text",
        "value": "Which SQL statement is true about correlated subqueries?"
      }
    ],
    "options": [
      {
        "label": "A",
        "type": "text",
        "value": "A correlated subquery can be executed independently of the outer query."
      },
      {
        "label": "B",
        "type": "text",
        "value": "A correlated subquery is evaluated once for each row processed by the outer query."
      },
      {
        "label": "C",
        "type": "text",
        "value": "Correlated subqueries cannot use the EXISTS keyword."
      },
      {
        "label": "D",
        "type": "text",
        "value": "Correlated subqueries do not allow the use of JOINs within them."
      }
    ],
    "correct": "B",
    "explanation": [
      {
        "type": "text",
        "value": "A correlated subquery is evaluated once for each row processed by the outer query because it refers to a column from the outer query, making it dependent on the outer query's rows."
      }
    ]
  },
  {
    "id": 5,
    "topic": "Basic SELECT Queries",
    "difficulty": "medium",
    "question": [
      {
        "type": "text",
        "value": "What will the following SQL query return: SELECT * FROM Employees WHERE Age > 30 AND Department = 'Sales';"
      }
    ],
    "options": [
      {
        "label": "A",
        "type": "text",
        "value": "Returns all records from the Employees table where Age is greater than 30 and Department is Sales."
      },
      {
        "label": "B",
        "type": "text",
        "value": "Returns the first record from the Employees table where Age is greater than 30 and Department is Sales."
      },
      {
        "label": "C",
        "type": "text",
        "value": "Returns all records from the Employees table where Age is less than 30 and Department is Sales."
      },
      {
        "label": "D",
        "type": "text",
        "value": "Returns nothing."
      }
    ],
    "correct": "A",
    "explanation": [
      {
        "type": "text",
        "value": "The SQL query uses AND logical operator to filter records where both conditions Age greater than 30 and Department being Sales must be true. It will return all matching records, not just the first one."
      }
    ]
  },
  {
    "id": 10,
    "topic": "User Privileges",
    "difficulty": "medium",
    "question": [
      {
        "type": "text",
        "value": "Which SQL command is used to remove specific privileges from a user in MySQL?"
      }
    ],
    "options": [
      {
        "label": "A",
        "type": "text",
        "value": "DROP USER"
      },
      {
        "label": "B",
        "type": "text",
        "value": "REVOKE"
      },
      {
        "label": "C",
        "type": "text",
        "value": "DELETE PRIVILEGES"
      },
      {
        "label": "D",
        "type": "text",
        "value": "REMOVE RIGHTS"
      }
    ],
    "correct": "B",
    "explanation": [
      {
        "type": "text",
        "value": "The REVOKE command is used in MySQL to remove specific privileges from a user, allowing for fine-grained access control."
      }
    ]
  },
  {
    "id": 6,
    "topic": "Data Handling with MySQL and Python",
    "difficulty": "medium",
    "question": [
      {
        "type": "text",
        "value": "In Python, which library is primarily used for integrating with MySQL for database operations?"
      }
    ],
    "options": [
      {
        "label": "A",
        "type": "text",
        "value": "sqlite3"
      },
      {
        "label": "B",
        "type": "text",
        "value": "pyodbc"
      },
      {
        "label": "C",
        "type": "text",
        "value": "PyMySQL"
      },
      {
        "label": "D",
        "type": "text",
        "value": "NumPy"
      }
    ],
    "correct": "C",
    "explanation": [
      {
        "type": "text",
        "value": "PyMySQL is a pure-Python MySQL client library, used to interact with a MySQL database from Python."
      }
    ]
  },
  {
    "id": 5,
    "topic": "Subqueries",
    "difficulty": "medium",
    "question": [
      {
        "type": "text",
        "value": "What is the result of the following SQL query? SELECT name FROM employees WHERE id IN (SELECT employee_id FROM sales WHERE amount > 5000);"
      }
    ],
    "options": [
      {
        "label": "A",
        "type": "text",
        "value": "Returns names of employees with sales greater than $5000"
      },
      {
        "label": "B",
        "type": "text",
        "value": "Returns the total sales amount greater than $5000"
      },
      {
        "label": "C",
        "type": "text",
        "value": "Returns the employee IDs with sales less than $5000"
      },
      {
        "label": "D",
        "type": "text",
        "value": "Returns an error message"
      }
    ],
    "correct": "A",
    "explanation": [
      {
        "type": "text",
        "value": "The query uses a subquery to first select employee IDs from the sales table where the sales amount is greater than $5000. Then, it fetches the names of those employees from the employees table."
      }
    ]
  },
  {
    "id": 3,
    "topic": "Index Optimization",
    "difficulty": "medium",
    "question": [
      {
        "type": "text",
        "value": "Which type of index would be most appropriate for optimizing a query that searches based on range values in MySQL?"
      }
    ],
    "options": [
      {
        "label": "A",
        "type": "text",
        "value": "Hash Index"
      },
      {
        "label": "B",
        "type": "text",
        "value": "B-Tree Index"
      },
      {
        "label": "C",
        "type": "text",
        "value": "Full-text Index"
      },
      {
        "label": "D",
        "type": "text",
        "value": "Spatial Index"
      }
    ],
    "correct": "B",
    "explanation": [
      {
        "type": "text",
        "value": "B-Tree indexes are best suited for range queries as they store their records in a sorted manner, allowing for quick searches between two bounds."
      }
    ]
  },
  {
    "id": 2,
    "topic": "Aggregation Functions",
    "difficulty": "medium",
    "question": [
      {
        "type": "text",
        "value": "Which function is used to return the sum of a numeric column?"
      }
    ],
    "options": [
      {
        "label": "A",
        "type": "text",
        "value": "MAX()"
      },
      {
        "label": "B",
        "type": "text",
        "value": "COUNT()"
      },
      {
        "label": "C",
        "type": "text",
        "value": "SUM()"
      },
      {
        "label": "D",
        "type": "text",
        "value": "AVG()"
      }
    ],
    "correct": "C",
    "explanation": [
      {
        "type": "text",
        "value": "SUM() function is used to return the total sum of a numeric column."
      }
    ]
  },
  {
    "id": 1,
    "topic": "User Privileges",
    "difficulty": "medium",
    "question": [
      {
        "type": "text",
        "value": "Which SQL statement is used to add a user-defined privilege to a MySQL user?"
      }
    ],
    "options": [
      {
        "label": "A",
        "type": "text",
        "value": "GRANT PRIVILEGE"
      },
      {
        "label": "B",
        "type": "text",
        "value": "ADD PRIVILEGE"
      },
      {
        "label": "C",
        "type": "text",
        "value": "GRANT"
      },
      {
        "label": "D",
        "type": "text",
        "value": "UPDATE PRIVILEGES"
      }
    ],
    "correct": "C",
    "explanation": [
      {
        "type": "text",
        "value": "The GRANT statement is used to give user-defined privileges to a MySQL user. The other options are not valid SQL statements for granting privileges."
      }
    ]
  },
  {
    "id": 5,
    "topic": "Index Optimization",
    "difficulty": "medium",
    "question": [
      {
        "type": "text",
        "value": "When should you consider adding an index to a column in a MySQL database?"
      }
    ],
    "options": [
      {
        "label": "A",
        "type": "text",
        "value": "When the column is frequently used in WHERE clauses"
      },
      {
        "label": "B",
        "type": "text",
        "value": "When the table has fewer than ten rows"
      },
      {
        "label": "C",
        "type": "text",
        "value": "When the column contains primarily NULL values"
      },
      {
        "label": "D",
        "type": "text",
        "value": "When the column data type is VARCHAR"
      }
    ],
    "correct": "A",
    "explanation": [
      {
        "type": "text",
        "value": "Adding an index to a column used frequently in WHERE clauses can significantly speed up the performance of queries by reducing the number of rows to scan."
      }
    ]
  },
  {
    "id": 7,
    "topic": "Data Types",
    "difficulty": "medium",
    "question": [
      {
        "type": "text",
        "value": "Which of the following data types is NOT supported by MySQL?"
      }
    ],
    "options": [
      {
        "label": "A",
        "type": "text",
        "value": "DATETIME"
      },
      {
        "label": "B",
        "type": "text",
        "value": "VARCHAR"
      },
      {
        "label": "C",
        "type": "text",
        "value": "BOOLEAN"
      },
      {
        "label": "D",
        "type": "text",
        "value": "CURRENCY"
      }
    ],
    "correct": "D",
    "explanation": [
      {
        "type": "text",
        "value": "CURRENCY is not a supported data type in MySQL. MySQL supports DATETIME, VARCHAR, and BOOLEAN as data types."
      }
    ]
  },
  {
    "id": 8,
    "topic": "Performance Optimization",
    "difficulty": "hard",
    "question": [
      {
        "type": "text",
        "value": "Which technique is MOST effective for optimizing complex queries in a MySQL-backed application, considering both execution speed and maintainability?"
      }
    ],
    "options": [
      {
        "label": "A",
        "type": "text",
        "value": "Adding indexes to all columns used in the queries"
      },
      {
        "label": "B",
        "type": "text",
        "value": "Using complex JOIN operations for all related tables"
      },
      {
        "label": "C",
        "type": "text",
        "value": "Refactoring queries to use subqueries and temporary tables appropriately"
      },
      {
        "label": "D",
        "type": "text",
        "value": "Increasing the buffer pool size indiscriminately"
      }
    ],
    "correct": "C",
    "explanation": [
      {
        "type": "text",
        "value": "Refactoring queries to use subqueries and temporary tables, when used appropriately, can significantly improve both the execution speed of complex queries and their maintainability. It allows better management of data processing and can reduce the workload on the database server."
      }
    ]
  },
  {
    "id": 10,
    "topic": "Query Optimization Techniques",
    "difficulty": "hard",
    "question": [
      {
        "type": "text",
        "value": "Which of the following query optimizations involves restructuring a complex query into a simpler form, which might involve breaking it down into smaller subqueries?"
      }
    ],
    "options": [
      {
        "label": "A",
        "type": "text",
        "value": "Join optimization"
      },
      {
        "label": "B",
        "type": "text",
        "value": "Indexing"
      },
      {
        "label": "C",
        "type": "text",
        "value": "Query refactoring"
      },
      {
        "label": "D",
        "type": "text",
        "value": "Data normalization"
      }
    ],
    "correct": "C",
    "explanation": [
      {
        "type": "text",
        "value": "Query refactoring involves altering the structure of SQL queries to improve database performance, often by simplifying complex queries into smaller, more manageable parts."
      }
    ]
  },
  {
    "id": 10,
    "topic": "Grouping and Aggregations",
    "difficulty": "hard",
    "question": [
      {
        "type": "text",
        "value": "Given a table 'Employees' with columns 'Department' and 'Salary', which of the following queries will correctly return the average salary for each department excluding those departments where any employee earns over $100,000?"
      }
    ],
    "options": [
      {
        "label": "A",
        "type": "text",
        "value": "SELECT Department, AVG(Salary) FROM Employees GROUP BY Department HAVING MAX(Salary) <= 100000;"
      },
      {
        "label": "B",
        "type": "text",
        "value": "SELECT Department, AVG(Salary) FROM Employees WHERE Salary <= 100000 GROUP BY Department;"
      },
      {
        "label": "C",
        "type": "text",
        "value": "SELECT Department, AVG(Salary) FROM Employees WHERE MAX(Salary) <= 100000 GROUP BY Department;"
      },
      {
        "label": "D",
        "type": "text",
        "value": "SELECT Department, AVG(Salary) FROM Employees GROUP BY Department HAVING MIN(Salary) > 100000;"
      }
    ],
    "correct": "A",
    "explanation": [
      {
        "type": "text",
        "value": "Option A is correct because it groups the employees by department and calculates the average salary only for those groups where the maximum salary in the group does not exceed $100,000, effectively excluding departments with any employee earning over $100,000."
      }
    ]
  },
  {
    "id": 7,
    "topic": "Managing MySQL User Privileges",
    "difficulty": "hard",
    "question": [
      {
        "type": "text",
        "value": "Which SQL command should be used to revoke all privileges from a user on the 'employees' database, but still allow them to log into MySQL?"
      }
    ],
    "options": [
      {
        "label": "A",
        "type": "text",
        "value": "REVOKE ALL PRIVILEGES ON employees.* FROM user;"
      },
      {
        "label": "B",
        "type": "text",
        "value": "REVOKE ALL ON employees.* FROM user;"
      },
      {
        "label": "C",
        "type": "text",
        "value": "REVOKE ALL PRIVILEGES ON employees.* TO user;"
      },
      {
        "label": "D",
        "type": "text",
        "value": "DELETE PRIVILEGES ON employees.* FROM user;"
      }
    ],
    "correct": "A",
    "explanation": [
      {
        "type": "text",
        "value": "Option A is correct because REVOKE ALL PRIVILEGES ON database.* FROM user; specifically removes all granted permissions on the specified database for the user, while still allowing database login."
      }
    ]
  },
  {
    "id": 5,
    "topic": "Advanced Subqueries",
    "difficulty": "hard",
    "question": [
      {
        "type": "text",
        "value": "Given the following tables, employees(emp_id, name, manager_id) and projects(proj_id, proj_name, emp_id), which subquery correctly finds the names of employees who manage at least one other employee but are not assigned to any project?"
      }
    ],
    "options": [
      {
        "label": "A",
        "type": "text",
        "value": "SELECT name FROM employees WHERE emp_id IN (SELECT manager_id FROM employees) AND emp_id NOT IN (SELECT emp_id FROM projects)"
      },
      {
        "label": "B",
        "type": "text",
        "value": "SELECT name FROM employees WHERE emp_id IN (SELECT manager_id FROM projects) AND emp_id NOT IN (SELECT emp_id FROM employees)"
      },
      {
        "label": "C",
        "type": "text",
        "value": "SELECT name FROM employees WHERE manager_id IS NOT NULL AND emp_id NOT IN (SELECT emp_id FROM projects)"
      },
      {
        "label": "D",
        "type": "text",
        "value": "SELECT name FROM employees WHERE emp_id IN (SELECT manager_id FROM employees) AND emp_id IN (SELECT emp_id FROM projects)"
      }
    ],
    "correct": "A",
    "explanation": [
      {
        "type": "text",
        "value": "Option A is correct because it selects employees who are listed as a manager of at least one other employee and are not listed in any project. The subqueries correctly check for manager status and absence in the projects table."
      }
    ]
  },
  {
    "id": 2,
    "topic": "Privilege Management",
    "difficulty": "hard",
    "question": [
      {
        "type": "text",
        "value": "Which command is used to revoke all privileges from a user on a specific database in MySQL?"
      }
    ],
    "options": [
      {
        "label": "A",
        "type": "text",
        "value": "REVOKE ALL PRIVILEGES, GRANT OPTION FROM user@localhost;"
      },
      {
        "label": "B",
        "type": "text",
        "value": "REVOKE ALL PRIVILEGES ON databasename.* FROM user@localhost;"
      },
      {
        "label": "C",
        "type": "text",
        "value": "DROP USER user@localhost;"
      },
      {
        "label": "D",
        "type": "text",
        "value": "ALTER USER user@localhost REVOKE ALL;"
      }
    ],
    "correct": "B",
    "explanation": [
      {
        "type": "text",
        "value": "Option B is correct because 'REVOKE ALL PRIVILEGES ON databasename.* FROM user@localhost;' specifically revokes all privileges from the user on the specified database. Other options do not specify a database or incorrectly format the command."
      }
    ]
  },
  {
    "id": 2,
    "topic": "Query Execution Plans",
    "difficulty": "hard",
    "question": [
      {
        "type": "text",
        "value": "In MySQL, what is the primary benefit of using the 'EXPLAIN' statement on a query?"
      }
    ],
    "options": [
      {
        "label": "A",
        "type": "text",
        "value": "It modifies the query to run faster by automatically optimizing it."
      },
      {
        "label": "B",
        "type": "text",
        "value": "It provides metadata about the tables involved in the query."
      },
      {
        "label": "C",
        "type": "text",
        "value": "It shows how MySQL executes a query, including details about how tables are joined and in which order."
      },
      {
        "label": "D",
        "type": "text",
        "value": "It estimates the total cost of a query in terms of time only."
      }
    ],
    "correct": "C",
    "explanation": [
      {
        "type": "text",
        "value": "The 'EXPLAIN' statement is used to obtain a query execution plan, which shows how MySQL executes a query. This includes whether indexes are used, how tables are joined, and the order of joins, which is crucial for optimizing query performance."
      }
    ]
  },
  {
    "id": 1,
    "topic": "Securing MySQL Connections in Applications",
    "difficulty": "hard",
    "question": [
      {
        "type": "text",
        "value": "When integrating MySQL with a secure web application, which method ensures that MySQL server certificates are validated against a Certificate Authority (CA) during the SSL/TLS handshake?"
      }
    ],
    "options": [
      {
        "label": "A",
        "type": "text",
        "value": "Using the --require-secure-transport option"
      },
      {
        "label": "B",
        "type": "text",
        "value": "Setting the MYSQLI_OPT_SSL_VERIFY_SERVER_CERT option in mysqli"
      },
      {
        "label": "C",
        "type": "text",
        "value": "Enabling the --ssl-mode=VERIFY_IDENTITY option"
      },
      {
        "label": "D",
        "type": "text",
        "value": "Applying the --ssl-ca parameter in the connection string"
      }
    ],
    "correct": "C",
    "explanation": [
      {
        "type": "text",
        "value": "The --ssl-mode=VERIFY_IDENTITY option ensures that the MySQL client verifies the server's SSL certificate against the CA certificates specified by --ssl-ca or the system's default CA certificates."
      }
    ]
  },
  {
    "id": 9,
    "topic": "Advanced JOIN Operations",
    "difficulty": "hard",
    "question": [
      {
        "type": "text",
        "value": "What will be the output of the following SQL query assuming all tables are properly indexed and 'employees' table has 5000 rows and 'departments' table has 500 rows? SELECT COUNT(*) FROM employees RIGHT JOIN departments ON employees.department_id = departments.id WHERE employees.id IS NULL;"
      }
    ],
    "options": [
      {
        "label": "A",
        "type": "text",
        "value": "500"
      },
      {
        "label": "B",
        "type": "text",
        "value": "4500"
      },
      {
        "label": "C",
        "type": "text",
        "value": "5000"
      },
      {
        "label": "D",
        "type": "text",
        "value": "5500"
      }
    ],
    "correct": "B",
    "explanation": [
      {
        "type": "text",
        "value": "The RIGHT JOIN includes all records from the 'departments' table and the matched records from the 'employees' table. The condition 'employees.id IS NULL' filters out unmatching rows from the 'employees' table, which refers to departments without any employees. Since there are total 500 departments, and assuming all are not evenly distributed among employees, the returned count (4500) represents departments without employees."
      }
    ]
  },
  {
    "id": 3,
    "topic": "Complex Joins",
    "difficulty": "hard",
    "question": [
      {
        "type": "text",
        "value": "Considering a database with tables 'Orders' (order_id, customer_id, order_date) and 'Products' (product_id, product_name, price). You need to find the highest price product ordered by each customer. Which SQL statement correctly achieves this?"
      }
    ],
    "options": [
      {
        "label": "A",
        "type": "text",
        "value": "SELECT customer_id, MAX(price) FROM Orders JOIN Products ON Orders.product_id = Products.product_id GROUP BY customer_id;"
      },
      {
        "label": "B",
        "type": "text",
        "value": "SELECT customer_id, product_name FROM Orders JOIN Products ON Orders.product_id = Products.product_id WHERE price = (SELECT MAX(price) FROM Products);"
      },
      {
        "label": "C",
        "type": "text",
        "value": "SELECT customer_id, product_name, price FROM Orders JOIN Products ON Orders.product_id = Products.product_id ORDER BY price DESC LIMIT 1;"
      },
      {
        "label": "D",
        "type": "text",
        "value": "SELECT customer_id, MAX(price) AS HighestPrice FROM Orders JOIN Products ON Orders.product_id = Products.product_id GROUP BY customer_id, product_name;"
      }
    ],
    "correct": "A",
    "explanation": [
      {
        "type": "text",
        "value": "Option A correctly uses JOIN to combine the tables, GROUP BY to aggregate results per customer, and MAX to find the highest price for each customer."
      }
    ]
  }
]